dave/__init__.py
dave/run_time.py
dave-0.9.0.data/scripts/dave
dave-0.9.0.dist-info/DESCRIPTION.rst
dave-0.9.0.dist-info/METADATA
dave-0.9.0.dist-info/RECORD
dave-0.9.0.dist-info/WHEEL
dave-0.9.0.dist-info/metadata.json
dave-0.9.0.dist-info/top_level.txt
