Metadata-Version: 2.0
Name: dave
Version: 0.9.0
Summary: A command line utility that runs your command line scripts from a yaml script
Home-page: https://github.com/episodeyang/dave
Author: Ge Yang
Author-email: yangge1987@gmail.com
License: UNKNOWN
Keywords: dave,experiment,experimentation,script runner
Platform: UNKNOWN
Classifier: Development Status :: 4 - Beta
Classifier: Intended Audience :: Science/Research
Classifier: Programming Language :: Python :: 3
Requires-Dist: munch
Requires-Dist: params-proto
Requires-Dist: pathlib
Requires-Dist: pathos
Requires-Dist: ruamel.yaml
